rulesengine/__init__.py
rulesengine/common.py
rulesengine/rule.py
rulesengine/rulesengine.py
rulesengine-1.0.1.dist-info/LICENSE
rulesengine-1.0.1.dist-info/METADATA
rulesengine-1.0.1.dist-info/WHEEL
rulesengine-1.0.1.dist-info/top_level.txt
rulesengine-1.0.1.dist-info/RECORD
