Metadata-Version: 2.1
Name: rulesengine
Version: 1.0.1
Summary: A rules engine to clarify your pipelines development
Home-page: https://gitlab.guirimand.eu/tguirimand/rulesengine
Author: Thibaut Guirimand
Author-email: tguirimand@gmx.fr
License: MIT
Platform: UNKNOWN
Classifier: Programming Language :: Python :: 3
Classifier: License :: OSI Approved :: MIT License
Classifier: Operating System :: OS Independent
Classifier: Development Status :: 6 - Mature
Classifier: Intended Audience :: Developers
Classifier: Topic :: Software Development
Classifier: Environment :: Plugins
Requires-Python: >=3.6
